dash_mantine_react_table/DashMantineReactTable.py
dash_mantine_react_table/__init__.py
dash_mantine_react_table/_imports_.py
dash_mantine_react_table/dash_mantine_react_table.js
dash_mantine_react_table/metadata.json
dash_mantine_react_table/package-info.json
dash_mantine_react_table-0.0.1.dist-info/LICENSE
dash_mantine_react_table-0.0.1.dist-info/METADATA
dash_mantine_react_table-0.0.1.dist-info/WHEEL
dash_mantine_react_table-0.0.1.dist-info/top_level.txt
dash_mantine_react_table-0.0.1.dist-info/RECORD
