Metadata-Version: 2.1
Name: dash-mantine-react-table
Version: 0.0.1
Summary: The right datagrid for Dash when using Dash Mantine Components.
Author: Snehil Vijay <snehilvj@outlook.com>
License: MIT
Classifier: Framework :: Dash
License-File: LICENSE
